{"cameraMode":{"drawMode":0,"name":"Shaded","section":"Shading Mode"},"sceneLighting":true,"audioPlay":false,"sceneViewState":{"m_AlwaysRefresh":false,"showFog":true,"showSkybox":true,"showFlares":true,"showImageEffects":true,"showParticleSystems":true,"showVisualEffectGraphs":true,"m_FxEnabled":true},"in2DMode":false,"pivot":{"x":-6.96861457824707,"y":8.162252426147461,"z":-0.21217918395996095},"rotation":{"x":0.281453937292099,"y":-0.0040188925340771679,"z":0.0011828907299786807,"w":0.9595712423324585},"size":13.337955474853516,"orthographic":false}